jaccard_test/__init__.py
jaccard_test/jaccard.py
jaccard_test-0.0.1.dist-info/LICENSE.txt
jaccard_test-0.0.1.dist-info/METADATA
jaccard_test-0.0.1.dist-info/WHEEL
jaccard_test-0.0.1.dist-info/top_level.txt
jaccard_test-0.0.1.dist-info/RECORD
