Metadata-Version: 2.1
Name: jaccard-test
Version: 0.0.1
Summary: UNKNOWN
Home-page: UNKNOWN
Author: Tanuka Chattaraj
Author-email: tanuka@businessbrio.com
License: MIT
Platform: UNKNOWN
Classifier: Programming Language :: Python :: 3
Classifier: License :: OSI Approved :: MIT License
Classifier: Operating System :: OS Independent
License-File: LICENSE.txt
Requires-Dist: scipy
Requires-Dist: numpy
